{"algo":"IBS_Bidirectional(MinChildren)_Gap","inst":"insts/Taillard/tai20_5_7.txt","is_optimal":true,"stats":{"avg_branching_factor":4.809716599190283,"nb_eval":6,"nb_expanded":247,"nb_generated":1188,"nb_guide":1190,"nb_sols_created":0,"nb_trashed":20,"nodes_generated_per_sec":270597.15625,"time_searched":0.004390290006995201},"stats_pareto":[{"eval":1,"expanded":20,"generated":210,"goals":230,"guide":210,"root":1,"solutions":0,"t":0.0000901849998626858,"trashed":0,"v":1255},{"eval":1,"expanded":20,"generated":210,"goals":230,"guide":210,"root":1,"solutions":0,"t":0.00021616699814330786,"trashed":0,"v":1255},{"eval":2,"expanded":20,"generated":210,"goals":230,"guide":210,"root":1,"solutions":0,"t":0.00022258399985730648,"trashed":0,"v":1255},{"eval":3,"expanded":58,"generated":446,"goals":504,"guide":446,"root":2,"solutions":0,"t":0.0003562140045687556,"trashed":0,"v":1222},{"eval":3,"expanded":58,"generated":446,"goals":504,"guide":446,"root":2,"solutions":0,"t":0.0027826048899441957,"trashed":0,"v":1222},{"eval":4,"expanded":59,"generated":446,"goals":505,"guide":446,"root":2,"solutions":0,"t":0.0028011209797114134,"trashed":1,"v":1222},{"eval":4,"expanded":84,"generated":490,"goals":574,"guide":491,"root":3,"solutions":0,"t":0.0029631040524691343,"trashed":6,"v":1222},{"eval":5,"expanded":226,"generated":1175,"goals":1401,"guide":1176,"root":4,"solutions":0,"t":0.003532924922183156,"trashed":8,"v":1206},{"eval":5,"expanded":226,"generated":1175,"goals":1401,"guide":1176,"root":4,"solutions":0,"t":0.0041762408800423145,"trashed":8,"v":1206},{"eval":6,"expanded":233,"generated":1175,"goals":1408,"guide":1176,"root":4,"solutions":0,"t":0.004203766118735075,"trashed":15,"v":1206},{"eval":6,"expanded":247,"generated":1188,"goals":1435,"guide":1190,"root":5,"solutions":0,"t":0.004286327864974737,"trashed":20,"v":1206},{"eval":6,"expanded":247,"generated":1188,"goals":1435,"guide":1190,"root":5,"solutions":0,"t":0.004286652896553278,"trashed":20,"v":1206}]}