{"IBS":{"algo_name":"IBS_Bidirectional(MinChildren)_Walpha","is_optimal":false},"avg_branching_factor":162.24334818111004,"best_primal":22893,"inst":{"name":"/home/decrypt/dogs/dogs-pfsp/insts/Large/VFR400_40_4_Gap.txt"},"is_optimal":false,"nb_eval":24,"nb_expanded":7370127,"nb_generated":1195754081,"nb_guide":1195754084,"nb_sols_created":0,"nb_trashed":464545,"nodes_generated_per_sec":1660756.625,"primal_pareto_diagram":[{"eval":1,"expanded":400,"generated":80200,"goals":80600,"guide":80200,"initial":1,"primal":25388,"solutions":0,"time":0.05624208226799965,"trashed":0},{"eval":1,"expanded":400,"generated":80200,"goals":80600,"guide":80200,"initial":1,"primal":25388,"solutions":0,"time":0.057838425040245056,"trashed":0},{"eval":2,"expanded":400,"generated":80200,"goals":80600,"guide":80200,"initial":1,"primal":25388,"solutions":0,"time":0.057841669768095016,"trashed":0},{"eval":3,"expanded":1198,"generated":240199,"goals":241397,"guide":240199,"initial":2,"primal":24428,"solutions":0,"time":0.19414380192756653,"trashed":0},{"eval":3,"expanded":1198,"generated":240199,"goals":241397,"guide":240199,"initial":2,"primal":24428,"solutions":0,"time":0.19630837440490723,"trashed":0},{"eval":5,"expanded":1199,"generated":240200,"goals":241399,"guide":240199,"initial":2,"primal":24420,"solutions":0,"time":0.19631792604923248,"trashed":0},{"eval":5,"expanded":1199,"generated":240200,"goals":241399,"guide":240199,"initial":2,"primal":24420,"solutions":0,"time":0.21174636483192444,"trashed":0},{"eval":6,"expanded":1199,"generated":240200,"goals":241399,"guide":240199,"initial":2,"primal":24420,"solutions":0,"time":0.21174922585487366,"trashed":0},{"eval":7,"expanded":2793,"generated":559797,"goals":562590,"guide":559796,"initial":3,"primal":23728,"solutions":0,"time":0.4902293086051941,"trashed":0},{"eval":7,"expanded":2793,"generated":559797,"goals":562590,"guide":559796,"initial":3,"primal":23728,"solutions":0,"time":0.492384135723114,"trashed":0},{"eval":8,"expanded":2796,"generated":559797,"goals":562593,"guide":559796,"initial":3,"primal":23728,"solutions":0,"time":0.4924064874649048,"trashed":3},{"eval":9,"expanded":5979,"generated":1197585,"goals":1203564,"guide":1197584,"initial":4,"primal":23720,"solutions":0,"time":1.015926718711853,"trashed":14},{"eval":9,"expanded":5979,"generated":1197585,"goals":1203564,"guide":1197584,"initial":4,"primal":23720,"solutions":0,"time":1.0174440145492554,"trashed":14},{"eval":10,"expanded":5982,"generated":1197585,"goals":1203567,"guide":1197584,"initial":4,"primal":23720,"solutions":0,"time":1.0174568891525269,"trashed":17},{"eval":11,"expanded":12352,"generated":2474770,"goals":2487122,"guide":2474769,"initial":5,"primal":23371,"solutions":0,"time":1.5772490501403809,"trashed":17},{"eval":11,"expanded":12352,"generated":2474770,"goals":2487122,"guide":2474769,"initial":5,"primal":23371,"solutions":0,"time":1.5787769556045532,"trashed":17},{"eval":12,"expanded":12367,"generated":2474770,"goals":2487137,"guide":2474769,"initial":5,"primal":23371,"solutions":0,"time":1.5788322687149048,"trashed":32},{"eval":13,"expanded":25105,"generated":5028739,"goals":5053844,"guide":5028738,"initial":6,"primal":23212,"solutions":0,"time":2.7043378353118896,"trashed":32},{"eval":13,"expanded":25105,"generated":5028739,"goals":5053844,"guide":5028738,"initial":6,"primal":23212,"solutions":0,"time":2.7058756351470947,"trashed":32},{"eval":14,"expanded":25136,"generated":5028739,"goals":5053875,"guide":5028738,"initial":6,"primal":23212,"solutions":0,"time":2.7059879302978516,"trashed":63},{"eval":14,"expanded":48882,"generated":7977881,"goals":8026763,"guide":7977881,"initial":7,"primal":23212,"solutions":0,"time":4.8834638595581055,"trashed":3071},{"eval":15,"expanded":99828,"generated":18191639,"goals":18291467,"guide":18191639,"initial":8,"primal":23102,"solutions":0,"time":9.386221885681152,"trashed":3071},{"eval":15,"expanded":99828,"generated":18191639,"goals":18291467,"guide":18191639,"initial":8,"primal":23102,"solutions":0,"time":9.387743949890137,"trashed":3071},{"eval":16,"expanded":99955,"generated":18191639,"goals":18291594,"guide":18191639,"initial":8,"primal":23102,"solutions":0,"time":9.388227462768555,"trashed":3198},{"eval":17,"expanded":201845,"generated":37051682,"goals":37253527,"guide":37051682,"initial":9,"primal":23089,"solutions":0,"time":18.379941940307617,"trashed":3887},{"eval":17,"expanded":201845,"generated":37051682,"goals":37253527,"guide":37051682,"initial":9,"primal":23089,"solutions":0,"time":18.381481170654297,"trashed":3887},{"eval":18,"expanded":202100,"generated":37051682,"goals":37253782,"guide":37051682,"initial":9,"primal":23089,"solutions":0,"time":18.3824462890625,"trashed":4142},{"eval":19,"expanded":405766,"generated":77862728,"goals":78268494,"guide":77862728,"initial":10,"primal":22897,"solutions":0,"time":36.45561981201172,"trashed":4142},{"eval":19,"expanded":405766,"generated":77862728,"goals":78268494,"guide":77862728,"initial":10,"primal":22897,"solutions":0,"time":36.45718765258789,"trashed":4142},{"eval":20,"expanded":406277,"generated":77862728,"goals":78269005,"guide":77862728,"initial":10,"primal":22897,"solutions":0,"time":36.45912551879883,"trashed":4653},{"eval":20,"expanded":807022,"generated":141745216,"goals":142552238,"guide":141745217,"initial":11,"primal":22897,"solutions":0,"time":72.20011901855469,"trashed":26162},{"eval":21,"expanded":1619836,"generated":275152932,"goals":276772768,"guide":275152933,"initial":12,"primal":22894,"solutions":0,"time":143.9613800048828,"trashed":49128},{"eval":21,"expanded":1619836,"generated":275152932,"goals":276772768,"guide":275152933,"initial":12,"primal":22894,"solutions":0,"time":143.96307373046875,"trashed":49128},{"eval":22,"expanded":1620879,"generated":275152932,"goals":276773811,"guide":275152933,"initial":12,"primal":22894,"solutions":0,"time":143.9672088623047,"trashed":50171},{"eval":23,"expanded":3237850,"generated":469350623,"goals":472588473,"guide":469350624,"initial":13,"primal":22893,"solutions":0,"time":285.95465087890625,"trashed":178941},{"eval":23,"expanded":3237850,"generated":469350623,"goals":472588473,"guide":469350624,"initial":13,"primal":22893,"solutions":0,"time":285.956298828125,"trashed":178941},{"eval":24,"expanded":3237946,"generated":469350623,"goals":472588569,"guide":469350624,"initial":13,"primal":22893,"solutions":0,"time":285.956787109375,"trashed":179037},{"eval":24,"expanded":6417633,"generated":844671817,"goals":851089450,"guide":844671819,"initial":14,"primal":22893,"solutions":0,"time":570.9114379882812,"trashed":464545},{"eval":24,"expanded":7370127,"generated":1195754081,"goals":1203124208,"guide":1195754084,"initial":15,"primal":22893,"solutions":0,"time":720.004150390625,"trashed":464545},{"eval":24,"expanded":7370127,"generated":1195754081,"goals":1203124208,"guide":1195754084,"initial":15,"primal":22893,"solutions":0,"time":720.0054931640625,"trashed":464545}],"time_searched":720.005615234375}