{"IBS":{"algo_name":"IBS_Forward_Gap","is_optimal":false},"avg_branching_factor":275.5138868085775,"best_primal":30495,"inst":{"name":"/home/decrypt/dogs/dogs-pfsp/insts/Large/VFR500_20_5_Gap.txt"},"is_optimal":false,"nb_eval":48,"nb_expanded":9300157,"nb_generated":2562322403,"nb_guide":2562322394,"nb_sols_created":0,"nb_trashed":28987,"nodes_generated_per_sec":5694029.0,"primal_pareto_diagram":[{"eval":1,"expanded":500,"generated":125250,"goals":125750,"guide":125250,"initial":1,"primal":31030,"solutions":0,"time":0.016967065632343292,"trashed":0},{"eval":1,"expanded":500,"generated":125250,"goals":125750,"guide":125250,"initial":1,"primal":31030,"solutions":0,"time":0.018724387511610985,"trashed":0},{"eval":2,"expanded":500,"generated":125250,"goals":125750,"guide":125250,"initial":1,"primal":31030,"solutions":0,"time":0.018724961206316948,"trashed":0},{"eval":3,"expanded":1498,"generated":374992,"goals":376490,"guide":374992,"initial":2,"primal":31029,"solutions":0,"time":0.05388443171977997,"trashed":1},{"eval":3,"expanded":1498,"generated":374992,"goals":376490,"guide":374992,"initial":2,"primal":31029,"solutions":0,"time":0.05569673329591751,"trashed":1},{"eval":5,"expanded":1499,"generated":374993,"goals":376492,"guide":374992,"initial":2,"primal":31028,"solutions":0,"time":0.05569986253976822,"trashed":1},{"eval":5,"expanded":1499,"generated":374993,"goals":376492,"guide":374992,"initial":2,"primal":31028,"solutions":0,"time":0.07859326153993607,"trashed":1},{"eval":6,"expanded":1499,"generated":374993,"goals":376492,"guide":374992,"initial":2,"primal":31028,"solutions":0,"time":0.07859618961811066,"trashed":1},{"eval":7,"expanded":3493,"generated":874020,"goals":877513,"guide":874019,"initial":3,"primal":31025,"solutions":0,"time":0.1544383317232132,"trashed":4},{"eval":7,"expanded":3493,"generated":874020,"goals":877513,"guide":874019,"initial":3,"primal":31025,"solutions":0,"time":0.15625157952308655,"trashed":4},{"eval":8,"expanded":3496,"generated":874020,"goals":877516,"guide":874019,"initial":3,"primal":31025,"solutions":0,"time":0.156259685754776,"trashed":7},{"eval":9,"expanded":7482,"generated":1871325,"goals":1878807,"guide":1871324,"initial":4,"primal":31018,"solutions":0,"time":0.3025668263435364,"trashed":7},{"eval":9,"expanded":7482,"generated":1871325,"goals":1878807,"guide":1871324,"initial":4,"primal":31018,"solutions":0,"time":0.3044009506702423,"trashed":7},{"eval":11,"expanded":7483,"generated":1871326,"goals":1878809,"guide":1871324,"initial":4,"primal":31014,"solutions":0,"time":0.3044043183326721,"trashed":7},{"eval":11,"expanded":7483,"generated":1871326,"goals":1878809,"guide":1871324,"initial":4,"primal":31014,"solutions":0,"time":0.3153038024902344,"trashed":7},{"eval":12,"expanded":7489,"generated":1871326,"goals":1878815,"guide":1871324,"initial":4,"primal":31014,"solutions":0,"time":0.31532350182533264,"trashed":13},{"eval":13,"expanded":15459,"generated":3864319,"goals":3879778,"guide":3864317,"initial":5,"primal":31011,"solutions":0,"time":0.6473019123077393,"trashed":13},{"eval":13,"expanded":15459,"generated":3864319,"goals":3879778,"guide":3864317,"initial":5,"primal":31011,"solutions":0,"time":0.6556757092475891,"trashed":13},{"eval":14,"expanded":15474,"generated":3864319,"goals":3879793,"guide":3864317,"initial":5,"primal":31011,"solutions":0,"time":0.655783474445343,"trashed":28},{"eval":15,"expanded":31412,"generated":7850165,"goals":7881577,"guide":7850163,"initial":6,"primal":31007,"solutions":0,"time":1.3282873630523682,"trashed":29},{"eval":15,"expanded":31412,"generated":7850165,"goals":7881577,"guide":7850163,"initial":6,"primal":31007,"solutions":0,"time":1.3301589488983154,"trashed":29},{"eval":17,"expanded":31413,"generated":7850166,"goals":7881579,"guide":7850163,"initial":6,"primal":31002,"solutions":0,"time":1.3301620483398438,"trashed":29},{"eval":17,"expanded":31413,"generated":7850166,"goals":7881579,"guide":7850163,"initial":6,"primal":31002,"solutions":0,"time":1.3339588642120361,"trashed":29},{"eval":18,"expanded":31443,"generated":7850166,"goals":7881609,"guide":7850163,"initial":6,"primal":31002,"solutions":0,"time":1.334031581878662,"trashed":59},{"eval":19,"expanded":63317,"generated":15822055,"goals":15885372,"guide":15822052,"initial":7,"primal":31001,"solutions":0,"time":2.7079296112060547,"trashed":67},{"eval":19,"expanded":63317,"generated":15822055,"goals":15885372,"guide":15822052,"initial":7,"primal":31001,"solutions":0,"time":2.709829330444336,"trashed":67},{"eval":21,"expanded":63318,"generated":15822056,"goals":15885374,"guide":15822052,"initial":7,"primal":30998,"solutions":0,"time":2.7098326683044434,"trashed":67},{"eval":21,"expanded":63318,"generated":15822056,"goals":15885374,"guide":15822052,"initial":7,"primal":30998,"solutions":0,"time":2.713235855102539,"trashed":67},{"eval":22,"expanded":63380,"generated":15822056,"goals":15885436,"guide":15822052,"initial":7,"primal":30998,"solutions":0,"time":2.7133772373199463,"trashed":129},{"eval":23,"expanded":127126,"generated":31780627,"goals":31907753,"guide":31780623,"initial":8,"primal":30929,"solutions":0,"time":5.364069938659668,"trashed":131},{"eval":23,"expanded":127126,"generated":31780627,"goals":31907753,"guide":31780623,"initial":8,"primal":30929,"solutions":0,"time":5.366013050079346,"trashed":131},{"eval":24,"expanded":127253,"generated":31780627,"goals":31907880,"guide":31780623,"initial":8,"primal":30929,"solutions":0,"time":5.366281986236572,"trashed":258},{"eval":25,"expanded":254743,"generated":63687747,"goals":63942490,"guide":63687743,"initial":9,"primal":30694,"solutions":0,"time":10.769976615905762,"trashed":260},{"eval":25,"expanded":254743,"generated":63687747,"goals":63942490,"guide":63687743,"initial":9,"primal":30694,"solutions":0,"time":10.77183723449707,"trashed":260},{"eval":26,"expanded":254998,"generated":63687747,"goals":63942745,"guide":63687743,"initial":9,"primal":30694,"solutions":0,"time":10.772391319274902,"trashed":515},{"eval":27,"expanded":509964,"generated":127195089,"goals":127705053,"guide":127195085,"initial":10,"primal":30633,"solutions":0,"time":21.546510696411133,"trashed":518},{"eval":27,"expanded":509964,"generated":127195089,"goals":127705053,"guide":127195085,"initial":10,"primal":30633,"solutions":0,"time":21.54835319519043,"trashed":518},{"eval":29,"expanded":509965,"generated":127195090,"goals":127705055,"guide":127195085,"initial":10,"primal":30580,"solutions":0,"time":21.548357009887695,"trashed":518},{"eval":29,"expanded":509965,"generated":127195090,"goals":127705055,"guide":127195085,"initial":10,"primal":30580,"solutions":0,"time":21.557296752929688,"trashed":518},{"eval":31,"expanded":509969,"generated":127195091,"goals":127705060,"guide":127195085,"initial":10,"primal":30576,"solutions":0,"time":21.557313919067383,"trashed":521},{"eval":31,"expanded":509969,"generated":127195091,"goals":127705060,"guide":127195085,"initial":10,"primal":30576,"solutions":0,"time":21.581218719482422,"trashed":521},{"eval":33,"expanded":509970,"generated":127195092,"goals":127705062,"guide":127195085,"initial":10,"primal":30558,"solutions":0,"time":21.58123207092285,"trashed":521},{"eval":33,"expanded":509970,"generated":127195092,"goals":127705062,"guide":127195085,"initial":10,"primal":30558,"solutions":0,"time":21.61206817626953,"trashed":521},{"eval":35,"expanded":509971,"generated":127195093,"goals":127705064,"guide":127195085,"initial":10,"primal":30552,"solutions":0,"time":21.612085342407227,"trashed":521},{"eval":35,"expanded":509971,"generated":127195093,"goals":127705064,"guide":127195085,"initial":10,"primal":30552,"solutions":0,"time":21.618526458740234,"trashed":521},{"eval":37,"expanded":510420,"generated":127195094,"goals":127705514,"guide":127195085,"initial":10,"primal":30547,"solutions":0,"time":21.61996078491211,"trashed":969},{"eval":37,"expanded":510420,"generated":127195094,"goals":127705514,"guide":127195085,"initial":10,"primal":30547,"solutions":0,"time":21.628646850585938,"trashed":969},{"eval":38,"expanded":510475,"generated":127195094,"goals":127705569,"guide":127195085,"initial":10,"primal":30547,"solutions":0,"time":21.628828048706055,"trashed":1024},{"eval":39,"expanded":1019905,"generated":254079314,"goals":255099219,"guide":254079305,"initial":11,"primal":30540,"solutions":0,"time":43.079429626464844,"trashed":1311},{"eval":39,"expanded":1019905,"generated":254079314,"goals":255099219,"guide":254079305,"initial":11,"primal":30540,"solutions":0,"time":43.081302642822266,"trashed":1311},{"eval":41,"expanded":1019908,"generated":254079315,"goals":255099223,"guide":254079305,"initial":11,"primal":30537,"solutions":0,"time":43.08131408691406,"trashed":1313},{"eval":41,"expanded":1019908,"generated":254079315,"goals":255099223,"guide":254079305,"initial":11,"primal":30537,"solutions":0,"time":43.08656692504883,"trashed":1313},{"eval":43,"expanded":1019915,"generated":254079316,"goals":255099231,"guide":254079305,"initial":11,"primal":30532,"solutions":0,"time":43.08658981323242,"trashed":1319},{"eval":43,"expanded":1019915,"generated":254079316,"goals":255099231,"guide":254079305,"initial":11,"primal":30532,"solutions":0,"time":43.09071731567383,"trashed":1319},{"eval":45,"expanded":1019956,"generated":254079317,"goals":255099273,"guide":254079305,"initial":11,"primal":30530,"solutions":0,"time":43.090816497802734,"trashed":1359},{"eval":45,"expanded":1019956,"generated":254079317,"goals":255099273,"guide":254079305,"initial":11,"primal":30530,"solutions":0,"time":43.09461212158203,"trashed":1359},{"eval":46,"expanded":1020928,"generated":254079317,"goals":255100245,"guide":254079305,"initial":11,"primal":30530,"solutions":0,"time":43.09670639038086,"trashed":2331},{"eval":47,"expanded":2039286,"generated":508349388,"goals":510388674,"guide":508349376,"initial":12,"primal":30495,"solutions":0,"time":87.55310821533203,"trashed":2338},{"eval":47,"expanded":2039286,"generated":508349388,"goals":510388674,"guide":508349376,"initial":12,"primal":30495,"solutions":0,"time":87.55498504638672,"trashed":2338},{"eval":48,"expanded":2041333,"generated":508349388,"goals":510390721,"guide":508349376,"initial":12,"primal":30495,"solutions":0,"time":87.55924224853516,"trashed":4385},{"eval":48,"expanded":4068153,"generated":1013620089,"goals":1017688242,"guide":1013620078,"initial":13,"primal":30495,"solutions":0,"time":175.4327392578125,"trashed":13991},{"eval":48,"expanded":8138205,"generated":2024257135,"goals":2032395340,"guide":2024257125,"initial":14,"primal":30495,"solutions":0,"time":357.3779602050781,"trashed":28987},{"eval":48,"expanded":9300157,"generated":2562322403,"goals":2571622560,"guide":2562322394,"initial":15,"primal":30495,"solutions":0,"time":450.00006103515625,"trashed":28987},{"eval":48,"expanded":9300157,"generated":2562322403,"goals":2571622560,"guide":2562322394,"initial":15,"primal":30495,"solutions":0,"time":450.0007629394531,"trashed":28987}],"time_searched":450.00164794921875}