{"algo":"IBS_Bidirectional(MinChildren)_Alpha","inst":"insts/Taillard/tai50_10_4.txt","is_optimal":false,"stats":{"avg_branching_factor":10.784271550853916,"nb_eval":32,"nb_expanded":2303215,"nb_generated":24838496,"nb_guide":24838496,"nb_sols_created":0,"nb_trashed":121136,"nodes_generated_per_sec":1101833.5,"time_searched":22.542877197265625},"stats_pareto":[{"eval":1,"expanded":50,"generated":1275,"goals":1325,"guide":1275,"root":1,"solutions":0,"t":0.0012616609456017613,"trashed":0,"v":3195},{"eval":1,"expanded":50,"generated":1275,"goals":1325,"guide":1275,"root":1,"solutions":0,"t":0.001802830956876278,"trashed":0,"v":3195},{"eval":2,"expanded":50,"generated":1275,"goals":1325,"guide":1275,"root":1,"solutions":0,"t":0.0018191529670730233,"trashed":0,"v":3195},{"eval":3,"expanded":148,"generated":3320,"goals":3468,"guide":3320,"root":2,"solutions":0,"t":0.004051565192639828,"trashed":0,"v":3168},{"eval":3,"expanded":148,"generated":3320,"goals":3468,"guide":3320,"root":2,"solutions":0,"t":0.004627957008779049,"trashed":0,"v":3168},{"eval":4,"expanded":149,"generated":3320,"goals":3469,"guide":3320,"root":2,"solutions":0,"t":0.004650863818824291,"trashed":1,"v":3168},{"eval":5,"expanded":343,"generated":7080,"goals":7423,"guide":7080,"root":3,"solutions":0,"t":0.008886418305337429,"trashed":11,"v":3167},{"eval":5,"expanded":343,"generated":7080,"goals":7423,"guide":7080,"root":3,"solutions":0,"t":0.010830084793269634,"trashed":11,"v":3167},{"eval":6,"expanded":346,"generated":7080,"goals":7426,"guide":7080,"root":3,"solutions":0,"t":0.010850774124264717,"trashed":14,"v":3167},{"eval":7,"expanded":732,"generated":16142,"goals":16874,"guide":16142,"root":4,"solutions":0,"t":0.014268697239458561,"trashed":14,"v":3133},{"eval":7,"expanded":732,"generated":16142,"goals":16874,"guide":16142,"root":4,"solutions":0,"t":0.014534070156514645,"trashed":14,"v":3133},{"eval":8,"expanded":739,"generated":16142,"goals":16881,"guide":16142,"root":4,"solutions":0,"t":0.01455363817512989,"trashed":21,"v":3133},{"eval":8,"expanded":1360,"generated":24243,"goals":25603,"guide":24244,"root":5,"solutions":0,"t":0.020237738266587257,"trashed":69,"v":3133},{"eval":9,"expanded":2894,"generated":43167,"goals":46061,"guide":43168,"root":6,"solutions":0,"t":0.03145802766084671,"trashed":141,"v":3131},{"eval":9,"expanded":2894,"generated":43167,"goals":46061,"guide":43168,"root":6,"solutions":0,"t":0.03953017666935921,"trashed":141,"v":3131},{"eval":11,"expanded":2896,"generated":43168,"goals":46064,"guide":43168,"root":6,"solutions":0,"t":0.03955619037151337,"trashed":142,"v":3130},{"eval":11,"expanded":2896,"generated":43168,"goals":46064,"guide":43168,"root":6,"solutions":0,"t":0.042324092239141464,"trashed":142,"v":3130},{"eval":13,"expanded":2898,"generated":43169,"goals":46067,"guide":43168,"root":6,"solutions":0,"t":0.04235027730464935,"trashed":143,"v":3126},{"eval":13,"expanded":2898,"generated":43169,"goals":46067,"guide":43168,"root":6,"solutions":0,"t":0.0447654128074646,"trashed":143,"v":3126},{"eval":14,"expanded":2920,"generated":43169,"goals":46089,"guide":43168,"root":6,"solutions":0,"t":0.044820163398981094,"trashed":165,"v":3126},{"eval":15,"expanded":5953,"generated":86439,"goals":92392,"guide":86438,"root":7,"solutions":0,"t":0.06859896332025528,"trashed":217,"v":3114},{"eval":15,"expanded":5953,"generated":86439,"goals":92392,"guide":86438,"root":7,"solutions":0,"t":0.068873830139637,"trashed":217,"v":3114},{"eval":16,"expanded":6016,"generated":86439,"goals":92455,"guide":86438,"root":7,"solutions":0,"t":0.06895790249109268,"trashed":280,"v":3114},{"eval":17,"expanded":12054,"generated":153702,"goals":165756,"guide":153701,"root":8,"solutions":0,"t":0.1130119264125824,"trashed":630,"v":3113},{"eval":17,"expanded":12054,"generated":153702,"goals":165756,"guide":153701,"root":8,"solutions":0,"t":0.11329564452171326,"trashed":630,"v":3113},{"eval":18,"expanded":12181,"generated":153702,"goals":165883,"guide":153701,"root":8,"solutions":0,"t":0.11345989257097244,"trashed":757,"v":3113},{"eval":19,"expanded":24220,"generated":286638,"goals":310858,"guide":286637,"root":9,"solutions":0,"t":0.20045211911201477,"trashed":1588,"v":3111},{"eval":19,"expanded":24220,"generated":286638,"goals":310858,"guide":286637,"root":9,"solutions":0,"t":0.20073986053466797,"trashed":1588,"v":3111},{"eval":20,"expanded":24475,"generated":286638,"goals":311113,"guide":286637,"root":9,"solutions":0,"t":0.20108278095722198,"trashed":1843,"v":3111},{"eval":21,"expanded":48407,"generated":569587,"goals":617994,"guide":569586,"root":10,"solutions":0,"t":0.3773029148578644,"trashed":3327,"v":3108},{"eval":21,"expanded":48407,"generated":569587,"goals":617994,"guide":569586,"root":10,"solutions":0,"t":0.3775925636291504,"trashed":3327,"v":3108},{"eval":22,"expanded":48918,"generated":569587,"goals":618505,"guide":569586,"root":10,"solutions":0,"t":0.3782711923122406,"trashed":3838,"v":3108},{"eval":23,"expanded":96390,"generated":1068437,"goals":1164827,"guide":1068436,"root":11,"solutions":0,"t":0.7265862822532654,"trashed":6056,"v":3107},{"eval":23,"expanded":96390,"generated":1068437,"goals":1164827,"guide":1068436,"root":11,"solutions":0,"t":0.7269022464752197,"trashed":6056,"v":3107},{"eval":24,"expanded":97413,"generated":1068437,"goals":1165850,"guide":1068436,"root":11,"solutions":0,"t":0.7284705638885498,"trashed":7079,"v":3107},{"eval":25,"expanded":191983,"generated":2019263,"goals":2211246,"guide":2019262,"root":12,"solutions":0,"t":1.4328515529632568,"trashed":13030,"v":3106},{"eval":25,"expanded":191983,"generated":2019263,"goals":2211246,"guide":2019262,"root":12,"solutions":0,"t":1.4361974000930786,"trashed":13030,"v":3106},{"eval":26,"expanded":194030,"generated":2019263,"goals":2213293,"guide":2019262,"root":12,"solutions":0,"t":1.4396741390228271,"trashed":15077,"v":3106},{"eval":27,"expanded":382804,"generated":3782313,"goals":4165117,"guide":3782312,"root":13,"solutions":0,"t":2.908705711364746,"trashed":28529,"v":3105},{"eval":27,"expanded":382804,"generated":3782313,"goals":4165117,"guide":3782312,"root":13,"solutions":0,"t":2.9090592861175537,"trashed":28529,"v":3105},{"eval":28,"expanded":386899,"generated":3782313,"goals":4169212,"guide":3782312,"root":13,"solutions":0,"t":2.916328191757202,"trashed":32624,"v":3105},{"eval":29,"expanded":760391,"generated":7353067,"goals":8113458,"guide":7353066,"root":14,"solutions":0,"t":5.967768669128418,"trashed":50370,"v":3104},{"eval":29,"expanded":760391,"generated":7353067,"goals":8113458,"guide":7353066,"root":14,"solutions":0,"t":5.968255996704102,"trashed":50370,"v":3104},{"eval":30,"expanded":768582,"generated":7353067,"goals":8121649,"guide":7353066,"root":14,"solutions":0,"t":5.985528469085693,"trashed":58561,"v":3104},{"eval":31,"expanded":1510560,"generated":14251275,"goals":15761835,"guide":14251274,"root":15,"solutions":0,"t":12.643850326538086,"trashed":98418,"v":3103},{"eval":31,"expanded":1510560,"generated":14251275,"goals":15761835,"guide":14251274,"root":15,"solutions":0,"t":12.644224166870117,"trashed":98418,"v":3103},{"eval":32,"expanded":1526943,"generated":14251275,"goals":15778218,"guide":14251274,"root":15,"solutions":0,"t":12.690110206604004,"trashed":114801,"v":3103},{"eval":32,"expanded":2303215,"generated":24838496,"goals":27141711,"guide":24838496,"root":16,"solutions":0,"t":22.519163131713867,"trashed":121136,"v":3103},{"eval":32,"expanded":2303215,"generated":24838496,"goals":27141711,"guide":24838496,"root":16,"solutions":0,"t":22.542673110961914,"trashed":121136,"v":3103}]}